faginator/Faginator.py
faginator/__init__.py
faginator-0.3.6.dist-info/LICENSE
faginator-0.3.6.dist-info/METADATA
faginator-0.3.6.dist-info/WHEEL
faginator-0.3.6.dist-info/top_level.txt
faginator-0.3.6.dist-info/RECORD
