Metadata-Version: 2.1
Name: faginator
Version: 0.3.6
Summary: Simple paginator for py-cord with custom buttons. You can use it in responds, or default post messages
Home-page: https://github.com/Fadix47/faginator
Author: Fadix Meier
Author-email: fadix18123@gmail.com
Project-URL: Bug Tracker, https://github.com/Fadix47/faginator/issues
Classifier: Programming Language :: Python :: 3
Classifier: License :: OSI Approved :: MIT License
Classifier: Operating System :: OS Independent
Requires-Python: >=3.7
License-File: LICENSE
